pygrank/__init__.py
pygrank/__pycache__/__init__.cpython-310.pyc
pygrank/algorithms/__init__.py
pygrank/algorithms/convergence.py
pygrank/algorithms/__pycache__/__init__.cpython-310.pyc
pygrank/algorithms/__pycache__/convergence.cpython-310.pyc
pygrank/algorithms/autotune/__init__.py
pygrank/algorithms/autotune/hop_tuner.py
pygrank/algorithms/autotune/optimization.py
pygrank/algorithms/autotune/parameterized.py
pygrank/algorithms/autotune/selection.py
pygrank/algorithms/autotune/tuning.py
pygrank/algorithms/autotune/__pycache__/__init__.cpython-310.pyc
pygrank/algorithms/autotune/__pycache__/hop_tuner.cpython-310.pyc
pygrank/algorithms/autotune/__pycache__/optimization.cpython-310.pyc
pygrank/algorithms/autotune/__pycache__/parameterized.cpython-310.pyc
pygrank/algorithms/autotune/__pycache__/selection.cpython-310.pyc
pygrank/algorithms/autotune/__pycache__/tuning.cpython-310.pyc
pygrank/algorithms/filters/__init__.py
pygrank/algorithms/filters/abstract_filters.py
pygrank/algorithms/filters/adhoc.py
pygrank/algorithms/filters/krylov_space.py
pygrank/algorithms/filters/krylov_utils.py
pygrank/algorithms/filters/low_pass.py
pygrank/algorithms/filters/__pycache__/__init__.cpython-310.pyc
pygrank/algorithms/filters/__pycache__/krylov_utils.cpython-310.pyc
pygrank/algorithms/filters/abstract/__init__.py
pygrank/algorithms/filters/abstract/closed.py
pygrank/algorithms/filters/abstract/filter.py
pygrank/algorithms/filters/abstract/recursive.py
pygrank/algorithms/filters/abstract/__pycache__/__init__.cpython-310.pyc
pygrank/algorithms/filters/abstract/__pycache__/closed.cpython-310.pyc
pygrank/algorithms/filters/abstract/__pycache__/filter.cpython-310.pyc
pygrank/algorithms/filters/abstract/__pycache__/recursive.cpython-310.pyc
pygrank/algorithms/filters/adhoc/__init__.py
pygrank/algorithms/filters/adhoc/biased_kernel.py
pygrank/algorithms/filters/adhoc/dijkstra.py
pygrank/algorithms/filters/adhoc/heat_kernel.py
pygrank-0.2.14.dist-info/LICENSE
pygrank-0.2.14.dist-info/METADATA
pygrank-0.2.14.dist-info/WHEEL
pygrank-0.2.14.dist-info/top_level.txt
pygrank-0.2.14.dist-info/RECORD
