Metadata-Version: 2.1
Name: pygrank
Version: 0.2.14
Summary: Recommendation algorithms for large graphs
Home-page: https://pygrank.readthedocs.io
Author: Emmanouil (Manios) Krasanakis
Author-email: maniospas@hotmail.com
License: UNKNOWN
Platform: UNKNOWN
Classifier: Programming Language :: Python :: 3
Classifier: License :: OSI Approved :: Apache Software License
Classifier: Operating System :: OS Independent
License-File: LICENSE
Requires-Dist: scikit-learn
Requires-Dist: scipy
Requires-Dist: numpy
Requires-Dist: networkx
Requires-Dist: wget
